{"playerAnalisis":[{"gols":0,"assistencias":0,"minutes":55.333333333333336,"penalts":0,"chutes":0.6666666666666666,"amarelo":0,"vermelho":0,"defesas":0,"fouls":0,"desarmes":0.6666666666666666,"crosses":1,"time":"Flamengo","player":"matiasvinaflamengo","position":"LB","touches":[48,4,39],"games":3,"pontuacao":0.23199999999999998},{"gols":0,"assistencias":0,"minutes":69.75,"penalts":0,"chutes":1,"amarelo":0,"vermelho":0,"defesas":0,"fouls":1,"desarmes":1,"crosses":1.5,"time":"Flamengo","player":"ayrtonlucasflamengo","position":"LB","touches":[10,63,68,48],"games":4,"pontuacao":0.33475},{"gols":0,"assistencias":0,"minutes":90,"penalts":0,"chutes":0,"amarelo":0,"vermelho":0,"defesas":0,"fouls":1,"desarmes":1,"crosses":6,"time":"Internacional","player":"alexandrobernabeiinternacional","position":"LB","touches":[0],"games":1,"pontuacao":0.3},{"gols":0,"assistencias":0,"minutes":90,"penalts":0,"chutes":0.6666666666666666,"amarelo":0.3333333333333333,"vermelho":0,"defesas":0,"fouls":0.6666666666666666,"desarmes":1.3333333333333333,"crosses":0.6666666666666666,"time":"Internacional","player":"reneinternacional","position":"LB","touches":[0,62,62],"games":3,"pontuacao":0.29666666666666663},{"gols":0,"assistencias":0,"minutes":90,"penalts":0,"chutes":0,"amarelo":0,"vermelho":0,"defesas":0,"fouls":3.5,"desarmes":1,"crosses":2.5,"time":"Juventude","player":"gabrielinocenciojuventude","position":"LB","touches":[73,62],"games":2,"pontuacao":0.265},{"gols":0,"assistencias":0,"minutes":67.25,"penalts":0,"chutes":0.5,"amarelo":0.25,"vermelho":0,"defesas":0,"fouls":1,"desarmes":0.5,"crosses":2.25,"time":"Cruzeiro","player":"marloncruzeiro","position":"LB","touches":[0,0,54,71],"games":4,"pontuacao":0.16475},{"gols":0,"assistencias":0,"minutes":90,"penalts":0,"chutes":0,"amarelo":0,"vermelho":0,"defesas":0,"fouls":0,"desarmes":1,"crosses":1,"time":"Cruzeiro","player":"lucasvillalbacruzeiro","position":"LB","touches":[0],"games":1,"pontuacao":0.25},{"gols":0,"assistencias":0,"minutes":41.666666666666664,"penalts":0,"chutes":0.3333333333333333,"amarelo":0,"vermelho":0,"defesas":0,"fouls":0.3333333333333333,"desarmes":0.16666666666666666,"crosses":2.3333333333333335,"time":"Bragantino","player":"guilhermebragantino","position":"LB","touches":[10,42,17,0,13,51],"games":6,"pontuacao":0.12333333333333332},{"gols":0.25,"assistencias":0.25,"minutes":90,"penalts":0,"chutes":0.75,"amarelo":0.25,"vermelho":0,"defesas":0,"fouls":1.5,"desarmes":1.75,"crosses":2.5,"time":"Ath Paranaense","player":"lucasesquivelathparanaense","position":"LB","touches":[0,0,100,48],"games":4,"pontuacao":0.7275},{"gols":0,"assistencias":0,"minutes":34,"penalts":0,"chutes":0,"amarelo":0,"vermelho":0,"defesas":0,"fouls":0,"desarmes":0,"crosses":1,"time":"Grêmio","player":"maykgremio","position":"LB","touches":[27],"games":1,"pontuacao":0.044000000000000004},{"gols":0,"assistencias":0,"minutes":73,"penalts":0,"chutes":0.3333333333333333,"amarelo":0,"vermelho":0,"defesas":0,"fouls":0.6666666666666666,"desarmes":0.6666666666666666,"crosses":2.3333333333333335,"time":"Grêmio","player":"cuiabanogremio","position":"LB","touches":[57,55,70],"games":3,"pontuacao":0.22966666666666663},{"gols":0,"assistencias":0,"minutes":63,"penalts":0,"chutes":0,"amarelo":0,"vermelho":0,"defesas":0,"fouls":1,"desarmes":1,"crosses":2,"time":"Grêmio","player":"wesleygremio","position":"LB","touches":[43],"games":1,"pontuacao":0.23299999999999998},{"gols":0,"assistencias":0,"minutes":22,"penalts":0,"chutes":0,"amarelo":0,"vermelho":0,"defesas":0,"fouls":0.5,"desarmes":0,"crosses":0,"time":"Grêmio","player":"zeguilhermegremio","position":"LB","touches":[27,17],"games":2,"pontuacao":0.022},{"gols":0,"assistencias":0,"minutes":90,"penalts":0,"chutes":0,"amarelo":0,"vermelho":0,"defesas":0,"fouls":0.5,"desarmes":1.5,"crosses":10,"time":"Vasco da Gama","player":"lucaspitonvascodagama","position":"LB","touches":[68,86],"games":2,"pontuacao":0.415},{"gols":0,"assistencias":0,"minutes":90,"penalts":0,"chutes":1,"amarelo":0,"vermelho":0,"defesas":0,"fouls":0.5,"desarmes":1.5,"crosses":3,"time":"Bahia","player":"lucianojubabahia","position":"LB","touches":[83,54],"games":2,"pontuacao":0.44499999999999995},{"gols":0,"assistencias":0,"minutes":12,"penalts":0,"chutes":0,"amarelo":0,"vermelho":0,"defesas":0,"fouls":0,"desarmes":0,"crosses":0,"time":"Botafogo (RJ)","player":"raibotafogo(rj)","position":"LB","touches":[11],"games":1,"pontuacao":0.012},{"gols":0,"assistencias":0,"minutes":53.666666666666664,"penalts":0,"chutes":0,"amarelo":0.3333333333333333,"vermelho":0,"defesas":0,"fouls":0,"desarmes":1.3333333333333333,"crosses":2,"time":"Botafogo (RJ)","player":"fernandomarcalbotafogo(rj)","position":"LB","touches":[16,71,41],"games":3,"pontuacao":0.207},{"gols":0.125,"assistencias":0.25,"minutes":70.75,"penalts":0,"chutes":0.875,"amarelo":0,"vermelho":0,"defesas":0,"fouls":0.625,"desarmes":1.75,"crosses":2.25,"time":"Botafogo (RJ)","player":"hugobotafogo(rj)","position":"LB","touches":[45,51,31,11,71,48,44,63],"games":8,"pontuacao":0.66825},{"gols":0,"assistencias":0,"minutes":49.333333333333336,"penalts":0,"chutes":0.6666666666666666,"amarelo":0.3333333333333333,"vermelho":0,"defesas":0,"fouls":1.6666666666666667,"desarmes":1,"crosses":1,"time":"Palmeiras","player":"vanderlanpalmeiras","position":"LB","touches":[36,6,27],"games":3,"pontuacao":0.20933333333333334},{"gols":0,"assistencias":0,"minutes":47.5,"penalts":0,"chutes":0,"amarelo":0.5,"vermelho":0,"defesas":0,"fouls":0,"desarmes":0.5,"crosses":0.5,"time":"Criciúma","player":"migueltraucocriciuma","position":"LB","touches":[11,58],"games":2,"pontuacao":0.027499999999999997},{"gols":0,"assistencias":0,"minutes":9,"penalts":0,"chutes":0,"amarelo":0,"vermelho":0,"defesas":0,"fouls":0,"desarmes":1,"crosses":0,"time":"Atlético Mineiro","player":"rubensatleticomineiro","position":"LB","touches":[11],"games":1,"pontuacao":0.159},{"gols":0.25,"assistencias":0.5,"minutes":84,"penalts":0,"chutes":0.75,"amarelo":0.5,"vermelho":0,"defesas":0,"fouls":0.25,"desarmes":0,"crosses":4.5,"time":"Atlético Mineiro","player":"guilhermearanaatleticomineiro","position":"LB","touches":[75,89,68,101],"games":4,"pontuacao":0.554},{"gols":0,"assistencias":0,"minutes":12,"penalts":0,"chutes":1,"amarelo":0,"vermelho":0,"defesas":0,"fouls":0,"desarmes":0,"crosses":1,"time":"Fluminense","player":"isaacfluminense","position":"LB","touches":[10],"games":1,"pontuacao":0.122},{"gols":0,"assistencias":0,"minutes":66,"penalts":0,"chutes":0,"amarelo":0,"vermelho":0,"defesas":0,"fouls":3,"desarmes":1,"crosses":0,"time":"Fluminense","player":"diogobarbosafluminense","position":"LB","touches":[36],"games":1,"pontuacao":0.216},{"gols":0,"assistencias":0,"minutes":80,"penalts":0,"chutes":2,"amarelo":0,"vermelho":0,"defesas":0,"fouls":0.6666666666666666,"desarmes":1.3333333333333333,"crosses":6,"time":"Fluminense","player":"marcelofluminense","position":"LB","touches":[74,70,74],"games":3,"pontuacao":0.54},{"gols":0,"assistencias":0,"minutes":78.75,"penalts":0,"chutes":1,"amarelo":0.5,"vermelho":0,"defesas":0,"fouls":1.5,"desarmes":0.75,"crosses":0.25,"time":"Corinthians","player":"hugocorinthians","position":"LB","touches":[0,0,54,70],"games":4,"pontuacao":0.19374999999999998},{"gols":0,"assistencias":0,"minutes":85,"penalts":0,"chutes":0,"amarelo":1,"vermelho":0,"defesas":0,"fouls":3,"desarmes":0,"crosses":1,"time":"Vitória","player":"lucasestevesvitoria","position":"LB","touches":[35],"games":1,"pontuacao":-0.105},{"gols":0,"assistencias":0,"minutes":5,"penalts":0,"chutes":0,"amarelo":0,"vermelho":0,"defesas":0,"fouls":0,"desarmes":0,"crosses":0,"time":"Vitória","player":"josehugovitoria","position":"LB","touches":[7],"games":1,"pontuacao":0.005},{"gols":0,"assistencias":0,"minutes":90,"penalts":0,"chutes":1.5,"amarelo":0.5,"vermelho":0,"defesas":0,"fouls":1.5,"desarmes":0.5,"crosses":2.5,"time":"Atl Goianiense","player":"guilhermeromaoatlgoianiense","position":"LB","touches":[51,63],"games":2,"pontuacao":0.24},{"gols":0,"assistencias":0,"minutes":37,"penalts":0,"chutes":0,"amarelo":0,"vermelho":0,"defesas":0,"fouls":0,"desarmes":0,"crosses":0,"time":"Cuiabá","player":"ramoncuiaba","position":"LB","touches":[0],"games":1,"pontuacao":0.037},{"gols":0,"assistencias":0,"minutes":77.66666666666667,"penalts":0,"chutes":0.6666666666666666,"amarelo":0,"vermelho":0,"defesas":0,"fouls":0,"desarmes":2,"crosses":2,"time":"Cuiabá","player":"rikelmecuiaba","position":"LB","touches":[0,0,47],"games":3,"pontuacao":0.4643333333333333}],"mediaGeral":{"gols":0.08020004612014295,"assistencias":0.06143491294823013,"penalts":0.0073648103309120255,"chutes":0.8016949152542375,"amarelo":0.16347572927476076,"vermelho":0.011991237172835236,"defesas":0.14124293785310735,"fouls":0.7893116568661362,"desarmes":0.5937564856451056,"crosses":1.1297676697797765,"pontuacao":0.32524272166493684}}